Metadata-Version: 2.1
Name: PythonSpaceo
Version: 0.0.1
Summary: python basecode package(api,admin panel)
Home-page: UNKNOWN
Author: deepak
Author-email: deepak@example.com
License: MIT
Platform: UNKNOWN
